odoo8_addon_logistic_order_donation-8.0.0.2.0-py2.7-nspkg.pth
odoo_addons/logistic_order_donation/__openerp__.py
odoo_addons/logistic_order_donation/__init__.py
odoo_addons/logistic_order_donation/README.rst
odoo_addons/logistic_order_donation/view/sale_order.xml
odoo_addons/logistic_order_donation/i18n/logistic_order_donation.pot
odoo_addons/logistic_order_donation/model/sale_order.py
odoo_addons/logistic_order_donation/model/__init__.py
odoo_addons/logistic_order_donation/data/stock.xml
odoo_addons/logistic_order_donation/demo/donation.xml
odoo8_addon_logistic_order_donation-8.0.0.2.0.dist-info/top_level.txt
odoo8_addon_logistic_order_donation-8.0.0.2.0.dist-info/WHEEL
odoo8_addon_logistic_order_donation-8.0.0.2.0.dist-info/RECORD
odoo8_addon_logistic_order_donation-8.0.0.2.0.dist-info/metadata.json
odoo8_addon_logistic_order_donation-8.0.0.2.0.dist-info/DESCRIPTION.rst
odoo8_addon_logistic_order_donation-8.0.0.2.0.dist-info/METADATA
odoo8_addon_logistic_order_donation-8.0.0.2.0.dist-info/namespace_packages.txt
